CMakeLists.txt
CMakeUrls.cmake
HISTORY.rst
LICENSE_Apache_20
LICENSE_BSD_3
MANIFEST.in
README.rst
requirements-dev.txt
setup.cfg
setup.py
versioneer.py
cmake/_version.py
cmake_odidev.egg-info/PKG-INFO
cmake_odidev.egg-info/SOURCES.txt
cmake_odidev.egg-info/dependency_links.txt
cmake_odidev.egg-info/entry_points.txt
cmake_odidev.egg-info/not-zip-safe
cmake_odidev.egg-info/top_level.txt