Metadata-Version: 1.1
Name: cmake-odidev
Version: 3.16.4
Summary: CMake is an open-source, cross-platform family of tools designed to build, test and package software
Home-page: http://cmake.org/
Author: Jean-Christophe Fillion-Robin
Author-email: jchris.fillionr@kitware.com
License: Apache 2.0
Download-URL: https://cmake.org/download
Keywords: CMake build c++ fortran cross-platform cross-compilation
Platform: UNKNOWN
Classifier: License :: OSI Approved :: Apache Software License
Classifier: License :: OSI Approved :: BSD License
Classifier: Programming Language :: C
Classifier: Programming Language :: C++
Classifier: Programming Language :: Fortran
Classifier: Programming Language :: Python
Classifier: Operating System :: OS Independent
Classifier: Development Status :: 5 - Production/Stable
Classifier: Intended Audience :: Developers
Classifier: Topic :: Software Development :: Build Tools
